neuroharmony/__init__.py
neuroharmony/data/__init__.py
neuroharmony/data/collect_tools.py
neuroharmony/data/combine_tools.py
neuroharmony/data/rois.py
neuroharmony/models/__init__.py
neuroharmony/models/harmonization.py
neuroharmony/models/metrics.py
neuroharmony/models/mriqc.py
neuroharmony/models/neuroCombat.py
tests/__init__.py
tests/test_collect.py
tests/test_combat_harmonization.py
tests/test_combine.py
tests/test_neuroharmony.py
Neuroharmony-0.1.13.dist-info/LICENSE.md
Neuroharmony-0.1.13.dist-info/METADATA
Neuroharmony-0.1.13.dist-info/WHEEL
Neuroharmony-0.1.13.dist-info/entry_points.txt
Neuroharmony-0.1.13.dist-info/top_level.txt
Neuroharmony-0.1.13.dist-info/RECORD
