Metadata-Version: 2.1
Name: Neuroharmony
Version: 0.1.13
Summary: A tool to perform Freesurfer volume Harminization in unseen scanner.
Home-page: https://github.com/garciadias/Neuroharmony
Author: Rafael Garcia-Dias
Author-email: rafaelagd@gmail.com
License: MIT license
Keywords: Harminization,MRI,data science
Platform: UNKNOWN
Classifier: Development Status :: 2 - Pre-Alpha
Classifier: Intended Audience :: Developers
Classifier: License :: OSI Approved :: MIT License
Classifier: Natural Language :: English
Classifier: Programming Language :: Python :: 3.6
Classifier: Programming Language :: Python :: 3.7
Classifier: Programming Language :: Python :: 3.8
Requires-Python: >=3.6
License-File: LICENSE.md
Requires-Dist: numpy (>=1.16.1)
Requires-Dist: pandas (>=1.1.4)
Requires-Dist: scikit-learn (>=0.22.2.post1)
Requires-Dist: scipy (>=1.2.0)
Requires-Dist: tqdm (>=4.31.1)
Requires-Dist: joblib (>=0.14.1)
Requires-Dist: requests (>=2.25.1)
Provides-Extra: docs
Requires-Dist: sphinx ; extra == 'docs'
Requires-Dist: sphinx-gallery ; extra == 'docs'
Requires-Dist: sphinx-rtd-theme ; extra == 'docs'
Requires-Dist: numpydoc ; extra == 'docs'
Requires-Dist: matplotlib ; extra == 'docs'
Provides-Extra: tests
Requires-Dist: pytest ; extra == 'tests'
Requires-Dist: pytest-cov ; extra == 'tests'
